Metadata-Version: 1.1
Name: marathon-proxy-manager
Version: 0.1.5
Summary: Reverse proxy and load balancing configuration for marathon mesos environment
Home-page: https://github.com/michallula/marathon-proxy-manager
Author: Michał Lula
Author-email: michal.lula@lingaro.com
License: MIT
Download-URL: https://github.com/michallula/marathon-proxy-manager/tarball/0.1.5
Keywords: marathon,mesos,nginx,load-balancing,reverse proxy
Platform: UNKNOWN
